cachetable/__init__.py
cachetable/admin.py
cachetable/models.py
django_cachetable-0.0.2.dist-info/METADATA
django_cachetable-0.0.2.dist-info/RECORD
django_cachetable-0.0.2.dist-info/WHEEL
django_cachetable-0.0.2.dist-info/top_level.txt
